[
    {
        "question": "0 + 0",
        "answer": 0,
        "choices": [
            0,
            1,
            2,
            3
        ]
    },
    {
        "question": "1 + 0",
        "answer": 1,
        "choices": [
            1,
            2,
            3,
            4
        ]
    },
    {
        "question": "2 + 0",
        "answer": 2,
        "choices": [
            2,
            3,
            4,
            5
        ]
    },
    {
        "question": "3 + 0",
        "answer": 3,
        "choices": [
            3,
            4,
            5,
            6
        ]
    },
    {
        "question": "4 + 0",
        "answer": 4,
        "choices": [
            4,
            5,
            6,
            7
        ]
    },
    {
        "question": "5 + 0",
        "answer": 5,
        "choices": [
            5,
            6,
            7,
            8
        ]
    },
    {
        "question": "6 + 0",
        "answer": 6,
        "choices": [
            6,
            7,
            8,
            9
        ]
    },
    {
        "question": "7 + 0",
        "answer": 7,
        "choices": [
            7,
            8,
            9,
            10
        ]
    },
    {
        "question": "8 + 0",
        "answer": 8,
        "choices": [
            8,
            9,
            10,
            11
        ]
    },
    {
        "question": "9 + 0",
        "answer": 9,
        "choices": [
            9,
            10,
            11,
            12
        ]
    },
    {
        "question": "10 + 0",
        "answer": 10,
        "choices": [
            10,
            11,
            12,
            13
        ]
    },
    {
        "question": "11 + 0",
        "answer": 11,
        "choices": [
            11,
            12,
            13,
            14
        ]
    },
    {
        "question": "12 + 0",
        "answer": 12,
        "choices": [
            12,
            13,
            14,
            15
        ]
    },
    {
        "question": "13 + 0",
        "answer": 13,
        "choices": [
            13,
            14,
            15,
            16
        ]
    },
    {
        "question": "14 + 0",
        "answer": 14,
        "choices": [
            14,
            15,
            16,
            17
        ]
    },
    {
        "question": "15 + 0",
        "answer": 15,
        "choices": [
            15,
            16,
            17,
            18
        ]
    },
    {
        "question": "16 + 0",
        "answer": 16,
        "choices": [
            16,
            17,
            18,
            19
        ]
    },
    {
        "question": "17 + 0",
        "answer": 17,
        "choices": [
            17,
            18,
            19,
            20
        ]
    },
    {
        "question": "18 + 0",
        "answer": 18,
        "choices": [
            18,
            19,
            20,
            21
        ]
    },
    {
        "question": "19 + 0",
        "answer": 19,
        "choices": [
            19,
            20,
            21,
            22
        ]
    },
    {
        "question": "20 + 0",
        "answer": 20,
        "choices": [
            20,
            21,
            22,
            23
        ]
    },
    {
        "question": "21 + 0",
        "answer": 21,
        "choices": [
            21,
            22,
            23,
            24
        ]
    },
    {
        "question": "22 + 0",
        "answer": 22,
        "choices": [
            22,
            23,
            24,
            25
        ]
    },
    {
        "question": "23 + 0",
        "answer": 23,
        "choices": [
            23,
            24,
            25,
            26
        ]
    },
    {
        "question": "24 + 0",
        "answer": 24,
        "choices": [
            24,
            25,
            26,
            27
        ]
    },
    {
        "question": "25 + 0",
        "answer": 25,
        "choices": [
            25,
            26,
            27,
            28
        ]
    },
    {
        "question": "26 + 0",
        "answer": 26,
        "choices": [
            26,
            27,
            28,
            29
        ]
    },
    {
        "question": "27 + 0",
        "answer": 27,
        "choices": [
            27,
            28,
            29,
            30
        ]
    },
    {
        "question": "28 + 0",
        "answer": 28,
        "choices": [
            28,
            29,
            30,
            31
        ]
    },
    {
        "question": "29 + 0",
        "answer": 29,
        "choices": [
            29,
            30,
            31,
            32
        ]
    },
    {
        "question": "30 + 0",
        "answer": 30,
        "choices": [
            30,
            31,
            32,
            33
        ]
    },
    {
        "question": "31 + 0",
        "answer": 31,
        "choices": [
            31,
            32,
            33,
            34
        ]
    },
    {
        "question": "32 + 0",
        "answer": 32,
        "choices": [
            32,
            33,
            34,
            35
        ]
    },
    {
        "question": "33 + 0",
        "answer": 33,
        "choices": [
            33,
            34,
            35,
            36
        ]
    },
    {
        "question": "34 + 0",
        "answer": 34,
        "choices": [
            34,
            35,
            36,
            37
        ]
    },
    {
        "question": "35 + 0",
        "answer": 35,
        "choices": [
            35,
            36,
            37,
            38
        ]
    },
    {
        "question": "36 + 0",
        "answer": 36,
        "choices": [
            36,
            37,
            38,
            39
        ]
    },
    {
        "question": "37 + 0",
        "answer": 37,
        "choices": [
            37,
            38,
            39,
            40
        ]
    },
    {
        "question": "38 + 0",
        "answer": 38,
        "choices": [
            38,
            39,
            40,
            41
        ]
    },
    {
        "question": "39 + 0",
        "answer": 39,
        "choices": [
            39,
            40,
            41,
            42
        ]
    },
    {
        "question": "40 + 0",
        "answer": 40,
        "choices": [
            40,
            41,
            42,
            43
        ]
    },
    {
        "question": "41 + 0",
        "answer": 41,
        "choices": [
            41,
            42,
            43,
            44
        ]
    },
    {
        "question": "42 + 0",
        "answer": 42,
        "choices": [
            42,
            43,
            44,
            45
        ]
    },
    {
        "question": "43 + 0",
        "answer": 43,
        "choices": [
            43,
            44,
            45,
            46
        ]
    },
    {
        "question": "44 + 0",
        "answer": 44,
        "choices": [
            44,
            45,
            46,
            47
        ]
    },
    {
        "question": "45 + 0",
        "answer": 45,
        "choices": [
            45,
            46,
            47,
            48
        ]
    },
    {
        "question": "46 + 0",
        "answer": 46,
        "choices": [
            46,
            47,
            48,
            49
        ]
    },
    {
        "question": "47 + 0",
        "answer": 47,
        "choices": [
            47,
            48,
            49,
            50
        ]
    },
    {
        "question": "48 + 0",
        "answer": 48,
        "choices": [
            48,
            49,
            50,
            51
        ]
    },
    {
        "question": "49 + 0",
        "answer": 49,
        "choices": [
            49,
            50,
            51,
            52
        ]
    },
    {
        "question": "50 + 0",
        "answer": 50,
        "choices": [
            50,
            51,
            52,
            53
        ]
    },
    {
        "question": "51 + 0",
        "answer": 51,
        "choices": [
            51,
            52,
            53,
            54
        ]
    },
    {
        "question": "52 + 0",
        "answer": 52,
        "choices": [
            52,
            53,
            54,
            55
        ]
    },
    {
        "question": "53 + 0",
        "answer": 53,
        "choices": [
            53,
            54,
            55,
            56
        ]
    },
    {
        "question": "54 + 0",
        "answer": 54,
        "choices": [
            54,
            55,
            56,
            57
        ]
    },
    {
        "question": "55 + 0",
        "answer": 55,
        "choices": [
            55,
            56,
            57,
            58
        ]
    },
    {
        "question": "56 + 0",
        "answer": 56,
        "choices": [
            56,
            57,
            58,
            59
        ]
    },
    {
        "question": "57 + 0",
        "answer": 57,
        "choices": [
            57,
            58,
            59,
            60
        ]
    },
    {
        "question": "58 + 0",
        "answer": 58,
        "choices": [
            58,
            59,
            60,
            61
        ]
    },
    {
        "question": "59 + 0",
        "answer": 59,
        "choices": [
            59,
            60,
            61,
            62
        ]
    },
    {
        "question": "60 + 0",
        "answer": 60,
        "choices": [
            60,
            61,
            62,
            63
        ]
    },
    {
        "question": "61 + 0",
        "answer": 61,
        "choices": [
            61,
            62,
            63,
            64
        ]
    },
    {
        "question": "62 + 0",
        "answer": 62,
        "choices": [
            62,
            63,
            64,
            65
        ]
    },
    {
        "question": "63 + 0",
        "answer": 63,
        "choices": [
            63,
            64,
            65,
            66
        ]
    },
    {
        "question": "64 + 0",
        "answer": 64,
        "choices": [
            64,
            65,
            66,
            67
        ]
    },
    {
        "question": "65 + 0",
        "answer": 65,
        "choices": [
            65,
            66,
            67,
            68
        ]
    },
    {
        "question": "66 + 0",
        "answer": 66,
        "choices": [
            66,
            67,
            68,
            69
        ]
    },
    {
        "question": "67 + 0",
        "answer": 67,
        "choices": [
            67,
            68,
            69,
            70
        ]
    },
    {
        "question": "68 + 0",
        "answer": 68,
        "choices": [
            68,
            69,
            70,
            71
        ]
    },
    {
        "question": "69 + 0",
        "answer": 69,
        "choices": [
            69,
            70,
            71,
            72
        ]
    },
    {
        "question": "70 + 0",
        "answer": 70,
        "choices": [
            70,
            71,
            72,
            73
        ]
    },
    {
        "question": "71 + 0",
        "answer": 71,
        "choices": [
            71,
            72,
            73,
            74
        ]
    },
    {
        "question": "72 + 0",
        "answer": 72,
        "choices": [
            72,
            73,
            74,
            75
        ]
    },
    {
        "question": "73 + 0",
        "answer": 73,
        "choices": [
            73,
            74,
            75,
            76
        ]
    },
    {
        "question": "74 + 0",
        "answer": 74,
        "choices": [
            74,
            75,
            76,
            77
        ]
    },
    {
        "question": "75 + 0",
        "answer": 75,
        "choices": [
            75,
            76,
            77,
            78
        ]
    },
    {
        "question": "76 + 0",
        "answer": 76,
        "choices": [
            76,
            77,
            78,
            79
        ]
    },
    {
        "question": "77 + 0",
        "answer": 77,
        "choices": [
            77,
            78,
            79,
            80
        ]
    },
    {
        "question": "78 + 0",
        "answer": 78,
        "choices": [
            78,
            79,
            80,
            81
        ]
    },
    {
        "question": "79 + 0",
        "answer": 79,
        "choices": [
            79,
            80,
            81,
            82
        ]
    },
    {
        "question": "80 + 0",
        "answer": 80,
        "choices": [
            80,
            81,
            82,
            83
        ]
    },
    {
        "question": "81 + 0",
        "answer": 81,
        "choices": [
            81,
            82,
            83,
            84
        ]
    },
    {
        "question": "82 + 0",
        "answer": 82,
        "choices": [
            82,
            83,
            84,
            85
        ]
    },
    {
        "question": "83 + 0",
        "answer": 83,
        "choices": [
            83,
            84,
            85,
            86
        ]
    },
    {
        "question": "84 + 0",
        "answer": 84,
        "choices": [
            84,
            85,
            86,
            87
        ]
    },
    {
        "question": "85 + 0",
        "answer": 85,
        "choices": [
            85,
            86,
            87,
            88
        ]
    },
    {
        "question": "86 + 0",
        "answer": 86,
        "choices": [
            86,
            87,
            88,
            89
        ]
    },
    {
        "question": "87 + 0",
        "answer": 87,
        "choices": [
            87,
            88,
            89,
            90
        ]
    },
    {
        "question": "88 + 0",
        "answer": 88,
        "choices": [
            88,
            89,
            90,
            91
        ]
    },
    {
        "question": "89 + 0",
        "answer": 89,
        "choices": [
            89,
            90,
            91,
            92
        ]
    },
    {
        "question": "90 + 0",
        "answer": 90,
        "choices": [
            90,
            91,
            92,
            93
        ]
    },
    {
        "question": "91 + 0",
        "answer": 91,
        "choices": [
            91,
            92,
            93,
            94
        ]
    },
    {
        "question": "92 + 0",
        "answer": 92,
        "choices": [
            92,
            93,
            94,
            95
        ]
    },
    {
        "question": "93 + 0",
        "answer": 93,
        "choices": [
            93,
            94,
            95,
            96
        ]
    },
    {
        "question": "94 + 0",
        "answer": 94,
        "choices": [
            94,
            95,
            96,
            97
        ]
    },
    {
        "question": "95 + 0",
        "answer": 95,
        "choices": [
            95,
            96,
            97,
            98
        ]
    },
    {
        "question": "96 + 0",
        "answer": 96,
        "choices": [
            96,
            97,
            98,
            99
        ]
    },
    {
        "question": "97 + 0",
        "answer": 97,
        "choices": [
            97,
            98,
            99,
            100
        ]
    },
    {
        "question": "98 + 0",
        "answer": 98,
        "choices": [
            98,
            99,
            100,
            101
        ]
    },
    {
        "question": "99 + 0",
        "answer": 99,
        "choices": [
            99,
            100,
            101,
            102
        ]
    }
]